{
  "ultimo_update": "2026-02-01 09:31:53",
  "sinais": [
    {
      "jogo": "Museum Wonders",
      "tipo": "REI \ud83d\udc51",
      "horario": "09:31:52",
      "confianca": "97.9%"
    },
    {
      "jogo": "Dragon hatch",
      "tipo": "REI \ud83d\udc51",
      "horario": "09:31:52",
      "confianca": "97.7%"
    },
    {
      "jogo": "Gem Saviour",
      "tipo": "REI \ud83d\udc51",
      "horario": "09:31:52",
      "confianca": "97.7%"
    },
    {
      "jogo": "\u00d7",
      "tipo": "REI \ud83d\udc51",
      "horario": "09:31:52",
      "confianca": "100.0%"
    },
    {
      "jogo": "Compartilhe com seus amigos para aumentar suas chances de ganhar!\u00daltima ganhadora @RAYSSAMFERNANDES",
      "tipo": "REI \ud83d\udc51",
      "horario": "09:31:52",
      "confianca": "100.0%"
    }
  ]
}