{
  "ultimo_update": "2026-02-01 19:16:23",
  "sinais": [
    {
      "jogo": "Groundhog Harvest",
      "tipo": "REI \ud83d\udc51",
      "horario": "19:16:22",
      "confianca": "97.9%"
    },
    {
      "jogo": "Caishen Wins",
      "tipo": "REI \ud83d\udc51",
      "horario": "19:16:22",
      "confianca": "97.9%"
    },
    {
      "jogo": "\u00d7",
      "tipo": "REI \ud83d\udc51",
      "horario": "19:16:22",
      "confianca": "100.0%"
    },
    {
      "jogo": "Compartilhe com seus amigos para aumentar suas chances de ganhar!\u00daltima ganhadora @RAYSSAMFERNANDES",
      "tipo": "REI \ud83d\udc51",
      "horario": "19:16:22",
      "confianca": "100.0%"
    }
  ]
}