{
  "ultimo_update": "2026-01-24 00:16:06",
  "sinais": [
    {
      "jogo": "Museum Wonders",
      "tipo": "REI \ud83d\udc51",
      "horario": "00:16:05",
      "confianca": "97.8%"
    },
    {
      "jogo": "Diamonds of Egypt",
      "tipo": "REI \ud83d\udc51",
      "horario": "00:16:05",
      "confianca": "97.7%"
    },
    {
      "jogo": "Hellvis Wild",
      "tipo": "REI \ud83d\udc51",
      "horario": "00:16:05",
      "confianca": "97.9%"
    },
    {
      "jogo": "Book of Sherlock",
      "tipo": "REI \ud83d\udc51",
      "horario": "00:16:05",
      "confianca": "97.7%"
    },
    {
      "jogo": "\u00d7",
      "tipo": "REI \ud83d\udc51",
      "horario": "00:16:05",
      "confianca": "100.0%"
    },
    {
      "jogo": "Compartilhe com seus amigos para aumentar suas chances de ganhar!\u00daltima ganhadora @RAYSSAMFERNANDES",
      "tipo": "REI \ud83d\udc51",
      "horario": "00:16:05",
      "confianca": "100.0%"
    }
  ]
}